areaid/__init__.py
areaid/area.py
areaid/data/aceh.json
areaid/data/bali.json
areaid/data/banten.json
areaid/data/bengkulu.json
areaid/data/daerah istimewa yogyakarta.json
areaid/data/daerah khusus ibukota jakarta.json
areaid/data/gorontalo.json
areaid/data/jambi.json
areaid/data/jawa barat.json
areaid/data/jawa tengah.json
areaid/data/jawa timur.json
areaid/data/kalimantan barat.json
areaid/data/kalimantan selatan.json
areaid/data/kalimantan tengah.json
areaid/data/kalimantan timur.json
areaid/data/kalimantan utara.json
areaid/data/kepulauan bangka belitung.json
areaid/data/kepulauan riau.json
areaid/data/lampung.json
areaid/data/maluku utara.json
areaid/data/maluku.json
areaid/data/nusa tenggara barat.json
areaid/data/nusa tenggara timur.json
areaid/data/papua barat.json
areaid/data/papua.json
areaid/data/riau.json
areaid/data/sulawesi barat.json
areaid/data/sulawesi selatan.json
areaid/data/sulawesi tengah.json
areaid/data/sulawesi tenggara.json
areaid/data/sulawesi utara.json
areaid/data/sumatra barat.json
areaid/data/sumatra selatan.json
areaid/data/sumatra utara.json
areaid/nama/provinsi.json
areaid-1.1.2.dist-info/METADATA
areaid-1.1.2.dist-info/WHEEL
areaid-1.1.2.dist-info/RECORD
