Metadata-Version: 2.1
Name: areaid
Version: 1.1.2
Summary: Indonesian regional data administration
License: MIT
Keywords: area,admin,indonesia,data,administration,administrasi,wilayah,daerah
Author: harigro
Author-email: trierbank@gmail.com
Requires-Python: >=3.10,<4.0
Classifier: Development Status :: 5 - Production/Stable
Classifier: Environment :: Console
Classifier: Intended Audience :: Developers
Classifier: License :: OSI Approved :: MIT License
Classifier: Programming Language :: Python
Classifier: Programming Language :: Python :: 3
Classifier: Programming Language :: Python :: 3.10
Classifier: Programming Language :: Python :: 3.11
Classifier: Programming Language :: Python :: 3 :: Only
Classifier: Programming Language :: Python :: 3.7
Classifier: Programming Language :: Python :: 3.8
Classifier: Programming Language :: Python :: 3.9
Classifier: Programming Language :: Python :: Implementation :: CPython
Classifier: Programming Language :: Python :: Implementation :: PyPy
Classifier: Topic :: Software Development :: Libraries :: Python Modules
Classifier: Topic :: Software Development :: Testing
Classifier: Topic :: Utilities
Project-URL: Documentation, https://github.com/harigro/areaid
Project-URL: Homepage, https://github.com/harigro/areaid
Project-URL: Repository, https://github.com/harigro/areaid
